adafruit_circuitpython_wiznet5k-7.4.1.dist-info/licenses/LICENSE
adafruit_wiznet5k/__init__.py
adafruit_wiznet5k/adafruit_wiznet5k.py
adafruit_wiznet5k/adafruit_wiznet5k_debug.py
adafruit_wiznet5k/adafruit_wiznet5k_dhcp.py
adafruit_wiznet5k/adafruit_wiznet5k_dns.py
adafruit_wiznet5k/adafruit_wiznet5k_socketpool.py
adafruit_circuitpython_wiznet5k-7.4.1.dist-info/METADATA
adafruit_circuitpython_wiznet5k-7.4.1.dist-info/WHEEL
adafruit_circuitpython_wiznet5k-7.4.1.dist-info/top_level.txt
adafruit_circuitpython_wiznet5k-7.4.1.dist-info/RECORD
