Metadata-Version: 2.4
Name: adafruit-circuitpython-wiznet5k
Version: 7.4.1
Summary: Pure-Python interface for WIZNET 5k ethernet modules.
Author-email: Adafruit Industries <circuitpython@adafruit.com>
License: MIT
Project-URL: Homepage, https://github.com/adafruit/Adafruit_CircuitPython_Wiznet5k
Keywords: adafruit,blinka,circuitpython,micropython,wiznet5k,ethernet,,wiznet,,w5500,,w5200,,internet,,iot
Classifier: Intended Audience :: Developers
Classifier: Topic :: Software Development :: Libraries
Classifier: Topic :: Software Development :: Embedded Systems
Classifier: Topic :: System :: Hardware
Classifier: License :: OSI Approved :: MIT License
Classifier: Programming Language :: Python :: 3
License-File: LICENSE
Requires-Dist: Adafruit-Blinka
Requires-Dist: adafruit-circuitpython-busdevice
Requires-Dist: adafruit-circuitpython-ticks
Provides-Extra: optional
Dynamic: license-file
